mock_serial/__init__.py
mock_serial/mock_serial.py
mock_serial/pytest.py
mock_serial/stub.py
mock_serial-0.0.1.dist-info/LICENCE
mock_serial-0.0.1.dist-info/METADATA
mock_serial-0.0.1.dist-info/WHEEL
mock_serial-0.0.1.dist-info/entry_points.txt
mock_serial-0.0.1.dist-info/top_level.txt
mock_serial-0.0.1.dist-info/RECORD
