Metadata-Version: 2.1
Name: mock_serial
Version: 0.0.1
Summary: A mock utility for testing serial devices
Home-page: https://github.com/benthorner/mock_serial
Author: Ben Thorner
Author-email: benthorner@users.noreply.github.com
License: UNKNOWN
Project-URL: Bug Tracker, https://github.com/benthorner/mock_serial/issues
Platform: UNKNOWN
Classifier: Programming Language :: Python :: 3
Classifier: License :: OSI Approved :: MIT License
Classifier: Operating System :: Unix
Classifier: Framework :: Pytest
Requires-Python: >=3.7
License-File: LICENCE
